<?xml version="1.0" encoding="utf-8"?>
<savedqueries xmlns:xsi="http://www.w3.org/2001/XMLSchema-instance">
  <savedquery>
    <isquickfindquery>0</isquickfindquery>
    <isprivate>0</isprivate>
    <isdefault>0</isdefault>
    <savedqueryid>{b0ba9c8c-e20f-43ba-bb26-c46c72cca425}</savedqueryid>
    <layoutxml>
      <grid name="resultset" jump="msfsi_number" select="1" icon="1" preview="1">
        <row name="result" id="msfsi_financialproductid">
          <cell name="msfsi_number" width="150" imageproviderfunctionname="" imageproviderwebresource="$webresource:" />
          <cell name="msfsi_customerid" width="150" imageproviderfunctionname="" imageproviderwebresource="$webresource:" />
          <cell name="msfsi_branchid" width="150" imageproviderfunctionname="" imageproviderwebresource="$webresource:" />
          <cell name="msfsi_availablebalance" width="125" imageproviderfunctionname="" imageproviderwebresource="$webresource:" />
        </row>
      </grid>
    </layoutxml>
    <querytype>0</querytype>
    <fetchxml>
      <fetch version="1.0" mapping="logical">
        <entity name="msfsi_financialproduct">
          <attribute name="msfsi_number" />
          <filter type="and">
            <condition attribute="statecode" operator="eq" value="1" />
          </filter>
          <attribute name="msfsi_customerid" />
          <attribute name="msfsi_branchid" />
          <attribute name="msfsi_availablebalance" />
          <order attribute="msfsi_number" descending="false" />
          <attribute name="msfsi_financialproductid" />
        </entity>
      </fetch>
    </fetchxml>
    <IntroducedVersion>1.0.0</IntroducedVersion>
    <LocalizedNames>
      <LocalizedName description="Inactive Financial Products" languagecode="1033" />
    </LocalizedNames>
  </savedquery>
</savedqueries>