<?xml version="1.0" encoding="utf-8"?>
<EntityRelationships xmlns:xsi="http://www.w3.org/2001/XMLSchema-instance">
  <EntityRelationship Name="business_unit_msfsi_bank" />
  <EntityRelationship Name="business_unit_msfsi_branch" />
  <EntityRelationship Name="business_unit_msfsi_collateral" />
  <EntityRelationship Name="business_unit_msfsi_financialproduct" />
  <EntityRelationship Name="business_unit_msfsi_kyc" />
  <EntityRelationship Name="business_unit_msfsi_limit" />
  <EntityRelationship Name="business_unit_msfsi_requestedfacility" />
  <EntityRelationship Name="business_unit_msfsi_syndicates" />
  <EntityRelationship Name="lk_msfsi_bank_createdby" />
  <EntityRelationship Name="lk_msfsi_bank_modifiedby" />
  <EntityRelationship Name="lk_msfsi_branch_createdby" />
  <EntityRelationship Name="lk_msfsi_branch_modifiedby" />
  <EntityRelationship Name="lk_msfsi_collateral_createdby" />
  <EntityRelationship Name="lk_msfsi_collateral_modifiedby" />
  <EntityRelationship Name="lk_msfsi_financialproduct_createdby" />
  <EntityRelationship Name="lk_msfsi_financialproduct_modifiedby" />
  <EntityRelationship Name="lk_msfsi_kyc_createdby" />
  <EntityRelationship Name="lk_msfsi_kyc_modifiedby" />
  <EntityRelationship Name="lk_msfsi_limit_createdby" />
  <EntityRelationship Name="lk_msfsi_limit_modifiedby" />
  <EntityRelationship Name="lk_msfsi_requestedfacility_createdby" />
  <EntityRelationship Name="lk_msfsi_requestedfacility_modifiedby" />
  <EntityRelationship Name="lk_msfsi_syndicates_createdby" />
  <EntityRelationship Name="lk_msfsi_syndicates_modifiedby" />
  <EntityRelationship Name="msfsi_account_contact_employerid" />
  <EntityRelationship Name="msfsi_account_msfsi_financialproduct_Customer" />
  <EntityRelationship Name="msfsi_account_msfsi_kyc_Customer" />
  <EntityRelationship Name="msfsi_account_msfsi_limit_companyid" />
  <EntityRelationship Name="msfsi_account_msfsi_requestedfacility_companyid" />
  <EntityRelationship Name="msfsi_contact_msfsi_financialproduct_Customer" />
  <EntityRelationship Name="msfsi_contact_msfsi_kyc_Customer" />
  <EntityRelationship Name="msfsi_contact_msfsi_kyc_primarycontact" />
  <EntityRelationship Name="msfsi_msfsi_bank_msfsi_branch_bankid" />
  <EntityRelationship Name="msfsi_msfsi_bank_msfsi_syndicates_bankid" />
  <EntityRelationship Name="msfsi_msfsi_branch_account_enrollmentbranchid" />
  <EntityRelationship Name="msfsi_msfsi_branch_contact_enrollmentbranchid" />
  <EntityRelationship Name="msfsi_msfsi_branch_contact_preferredbranchid" />
  <EntityRelationship Name="msfsi_msfsi_branch_msfsi_financialproduct_branchid" />
  <EntityRelationship Name="msfsi_msfsi_financialproduct_contact_defaultchargeaccountid" />
  <EntityRelationship Name="msfsi_msfsi_financialproduct_msfsi_collateral_financialproductid" />
  <EntityRelationship Name="msfsi_msfsi_financialproduct_msfsi_syndicates_loanid" />
  <EntityRelationship Name="msfsi_msfsi_limit_msfsi_financialproduct_limitid" />
  <EntityRelationship Name="msfsi_systemuser_msfsi_branch_branchmanagerid" />
  <EntityRelationship Name="owner_msfsi_bank" />
  <EntityRelationship Name="owner_msfsi_branch" />
  <EntityRelationship Name="owner_msfsi_collateral" />
  <EntityRelationship Name="owner_msfsi_financialproduct" />
  <EntityRelationship Name="owner_msfsi_kyc" />
  <EntityRelationship Name="owner_msfsi_limit" />
  <EntityRelationship Name="owner_msfsi_requestedfacility" />
  <EntityRelationship Name="owner_msfsi_syndicates" />
  <EntityRelationship Name="team_msfsi_bank" />
  <EntityRelationship Name="team_msfsi_branch" />
  <EntityRelationship Name="team_msfsi_collateral" />
  <EntityRelationship Name="team_msfsi_financialproduct" />
  <EntityRelationship Name="team_msfsi_kyc" />
  <EntityRelationship Name="team_msfsi_limit" />
  <EntityRelationship Name="team_msfsi_requestedfacility" />
  <EntityRelationship Name="team_msfsi_syndicates" />
  <EntityRelationship Name="TransactionCurrency_msfsi_collateral" />
  <EntityRelationship Name="TransactionCurrency_msfsi_financialproduct" />
  <EntityRelationship Name="TransactionCurrency_msfsi_limit" />
  <EntityRelationship Name="TransactionCurrency_msfsi_requestedfacility" />
  <EntityRelationship Name="TransactionCurrency_msfsi_syndicates" />
  <EntityRelationship Name="user_msfsi_bank" />
  <EntityRelationship Name="user_msfsi_branch" />
  <EntityRelationship Name="user_msfsi_collateral" />
  <EntityRelationship Name="user_msfsi_financialproduct" />
  <EntityRelationship Name="user_msfsi_kyc" />
  <EntityRelationship Name="user_msfsi_limit" />
  <EntityRelationship Name="user_msfsi_requestedfacility" />
  <EntityRelationship Name="user_msfsi_syndicates" />
</EntityRelationships>